backtrader_contrib/__init__.py
backtrader_contrib/loadmodule.py
backtrader_contrib/version.py
backtrader_contrib/analyzers/__init__.py
backtrader_contrib/brokers/__init__.py
backtrader_contrib/brokers/lucid/__init__.py
backtrader_contrib/brokers/lucid/ibapi/__init__.py
backtrader_contrib/brokers/lucid/ibapi/ibbroker.py
backtrader_contrib/commissions/__init__.py
backtrader_contrib/feeds/__init__.py
backtrader_contrib/feeds/lucid/__init__.py
backtrader_contrib/feeds/lucid/ibapi/__init__.py
backtrader_contrib/feeds/lucid/ibapi/ibdata.py
backtrader_contrib/filters/__init__.py
backtrader_contrib/framework/__init__.py
backtrader_contrib/framework/lucid/__init__.py
backtrader_contrib/framework/lucid/data/__init__.py
backtrader_contrib/framework/lucid/data/data_adjuster.py
backtrader_contrib/framework/lucid/data/input_ouput.py
backtrader_contrib/framework/lucid/utils/__init__.py
backtrader_contrib/framework/lucid/utils/allocator_base.py
backtrader_contrib/framework/lucid/utils/analytics.py
backtrader_contrib/framework/lucid/utils/order_management.py
backtrader_contrib/framework/lucid/utils/portfolio.py
backtrader_contrib/framework/lucid/utils/run_backtest.py
backtrader_contrib/framework/lucid/utils/strategy_generic.py
backtrader_contrib/indicators/__init__.py
backtrader_contrib/observers/__init__.py
backtrader_contrib/signals/__init__.py
backtrader_contrib/sizers/__init__.py
backtrader_contrib/stores/__init__.py
backtrader_contrib/stores/lucid/__init__.py
backtrader_contrib/stores/lucid/ibapi/__init__.py
backtrader_contrib/stores/lucid/ibapi/custom_logger.py
backtrader_contrib/stores/lucid/ibapi/ibstore.py
backtrader_contrib/strategies/__init__.py
backtrader_contrib/strategies/lucid/__init__.py
backtrader_contrib/strategies/lucid/adaptive_asset_allocation/__init__.py
backtrader_contrib/strategies/lucid/adaptive_asset_allocation/adaptive_allocation.py
backtrader_contrib/strategies/lucid/adaptive_asset_allocation/adaptive_allocation_methods.py
backtrader_contrib_lucidinvestor-0.4.5.dist-info/licenses/LICENSE
backtrader_contrib_lucidinvestor-0.4.5.dist-info/licenses/LICENSE.apache
backtrader_contrib_lucidinvestor-0.4.5.dist-info/licenses/LICENSE.bsd3
backtrader_contrib_lucidinvestor-0.4.5.dist-info/licenses/LICENSE.gplv3
backtrader_contrib_lucidinvestor-0.4.5.dist-info/licenses/LICENSE.mit
backtrader_contrib_lucidinvestor-0.4.5.dist-info/METADATA
backtrader_contrib_lucidinvestor-0.4.5.dist-info/WHEEL
backtrader_contrib_lucidinvestor-0.4.5.dist-info/top_level.txt
backtrader_contrib_lucidinvestor-0.4.5.dist-info/RECORD
