Metadata-Version: 2.4
Name: backtrader-contrib-lucidinvestor
Version: 0.4.5
Summary: Backtrader strategies and indicators from LucidInvestor
Author: LucidInvestor
Author-email: info@lucidinvestor.ca
License: GPLv3+
Classifier: Development Status :: 5 - Production/Stable
Classifier: Intended Audience :: Developers
Classifier: Intended Audience :: Financial and Insurance Industry
Classifier: Topic :: Software Development
Classifier: Topic :: Office/Business :: Financial
Classifier: Programming Language :: Python :: 3
Classifier: Operating System :: OS Independent
Requires-Python: >=3.6
License-File: LICENSE
License-File: LICENSE.apache
License-File: LICENSE.bsd3
License-File: LICENSE.gplv3
License-File: LICENSE.mit
Requires-Dist: backtrader-lucidinvestor
Requires-Dist: cython
Requires-Dist: matplotlib
Requires-Dist: numpy==1.26.4
Requires-Dist: pandas==1.5.3
Requires-Dist: pandas-datareader==0.10.0
Requires-Dist: python-dateutil
Requires-Dist: pytz
Requires-Dist: scipy==1.10.1
Requires-Dist: yfinance==0.2.63
Requires-Dist: curl_cffi
Requires-Dist: pandas_market_calendars==4.1.4
Requires-Dist: pyfolio-reloaded==0.9.5
Requires-Dist: pyportfolioopt==1.5.5
Requires-Dist: cvxpy==1.3.2
Requires-Dist: arch
Dynamic: license-file
Dynamic: requires-dist
